Workspace/top.sv
`define DEBUG

module leading_1_detector_48bit
    (
        input wire  [47:0]  tmp,
        output reg  [7:0]   ret
    );
    always_comb begin
        if(tmp[47]) begin
            ret = 8'd47;
        end
        else if(tmp[46]) begin
        ret = 8'd46;
        end
        else if(tmp[45]) begin
        ret = 8'd45;
        end
        else if(tmp[44]) begin
        ret = 8'd44;
        end
        else if(tmp[43]) begin
        ret = 8'd43;
        end
        else if(tmp[42]) begin
        ret = 8'd42;
        end
        else if(tmp[41]) begin
        ret = 8'd41;
        end
        else if(tmp[40]) begin
        ret = 8'd40;
        end
        else if(tmp[39]) begin
        ret = 8'd39;
        end
        else if(tmp[38]) begin
        ret = 8'd38;
        end
        else if(tmp[37]) begin
        ret = 8'd37;
        end
        else if(tmp[36]) begin
        ret = 8'd36;
        end
        else if(tmp[35]) begin
        ret = 8'd35;
        end
        else if(tmp[34]) begin
        ret = 8'd34;
        end
        else if(tmp[33]) begin
        ret = 8'd33;
        end
        else if(tmp[32]) begin
        ret = 8'd32;
        end
        else if(tmp[31]) begin
        ret = 8'd31;
        end
        else if(tmp[30]) begin
        ret = 8'd30;
        end
        else if(tmp[29]) begin
        ret = 8'd29;
        end
        else if(tmp[28]) begin
        ret = 8'd28;
        end
        else if(tmp[27]) begin
        ret = 8'd27;
        end
        else if(tmp[26]) begin
        ret = 8'd26;
        end
        else if(tmp[25]) begin
        ret = 8'd25;
        end
        else if(tmp[24]) begin
        ret = 8'd24;
        end
        else if(tmp[23]) begin
        ret = 8'd23;
        end
        else if(tmp[22]) begin
        ret = 8'd22;
        end
        else if(tmp[21]) begin
        ret = 8'd21;
        end
        else if(tmp[20]) begin
        ret = 8'd20;
        end
        else if(tmp[19]) begin
        ret = 8'd19;
        end
        else if(tmp[18]) begin
        ret = 8'd18;
        end
        else if(tmp[17]) begin
        ret = 8'd17;
        end
        else if(tmp[16]) begin
        ret = 8'd16;
        end
        else if(tmp[15]) begin
        ret = 8'd15;
        end
        else if(tmp[14]) begin
        ret = 8'd14;
        end
        else if(tmp[13]) begin
        ret = 8'd13;
        end
        else if(tmp[12]) begin
        ret = 8'd12;
        end
        else if(tmp[11]) begin
        ret = 8'd11;
        end
        else if(tmp[10]) begin
        ret = 8'd10;
        end
        else if(tmp[9]) begin
        ret = 8'd9;
        end
        else if(tmp[8]) begin
        ret = 8'd8;
        end
        else if(tmp[7]) begin
        ret = 8'd7;
        end
        else if(tmp[6]) begin
        ret = 8'd6;
        end
        else if(tmp[5]) begin
        ret = 8'd5;
        end
        else if(tmp[4]) begin
        ret = 8'd4;
        end
        else if(tmp[3]) begin
        ret = 8'd3;
        end
        else if(tmp[2]) begin
        ret = 8'd2;
        end
        else if(tmp[1]) begin
        ret = 8'd1;
        end
        else if(tmp[0]) begin
        ret = 8'd0;
        end
        else begin
        ret = 8'hFF;
        end
    end
endmodule

module FP32_Multiplier_Combinatorial
    (
        input wire [31:0] alpha,
        input wire [31:0] bravo,
        output reg [31:0] delta
        // VALID, READY handshake 는 어떻게 구현?
    );

    /*
        IEEE 754 Floating Point
        1 Bit | 8 Bit | 23 Bit
    */

    // 기본적으로, EA 및 EB는 unsigned 취급.
    wire [7:0]   EA_Original, EB_Original, EA, EB;
    wire signed [7:0]   Larger_E, EA_minus_EB, EB_minus_EA, Right_Shift;
    wire signed [8:0]   EA_plus_EB, EA_plus_EB_minus_254;
    wire         EA0, EB0, EA1, EB1, E_LeftBig, E_RightBig, E_Equal;

    assign EA_Original = alpha[30:23];
    assign EB_Original = bravo[30:23];

    assign EA0 = ((EA_Original == 8'd0) ? 1'b1 : 1'b0);
    assign EB0 = ((EB_Original == 8'd0) ? 1'b1 : 1'b0);
    assign EA1 = ((EA_Original == 8'hFF) ? 1'b1 : 1'b0);
    assign EB1 = ((EB_Original == 8'hFF) ? 1'b1 : 1'b0);

    assign EA_minus_EB = EA_Original - EB_Original;
    assign EB_minus_EA = EB_Original - EA_Original;

    assign E_RightBig = ((EA_Original < EB_Original) ? 1'b1 : 1'b0);
    assign E_LeftBig = ((EA_Original > EB_Original) ? 1'b1 : 1'b0);
    assign E_Equal = !(E_RightBig | E_LeftBig);

    assign Larger_E = ((E_LeftBig) ? EA_Original : EB_Original);
    assign Right_Shift = ((E_LeftBig) ? EA_minus_EB : EB_minus_EA) - {7'd0 , (EA0 ^ EB0)};

    assign EA = EA_Original + {7'd0 ,EA0};
    assign EB = EB_Original + {7'd0, EB0};

    assign EA_plus_EB = EA + EB; // 9Bit 해야 안전하지 않아? 맞겠지?
    assign EA_plus_EB_minus_254 = EA_plus_EB - 9'd254;

    /********************** Get Sign ************************/
    wire SA, SB, final_sign;
    assign SA = alpha[31];
    assign SB = bravo[31];
    assign final_sign = SA ^ SB;
    /**********************　　　Setting Up Multiply Mantissa　　　　****************************/

    wire    [22:0]   MA, MB; // Hidden 1 없음에 유의
    wire    [23:0]   isDenorm1, isDenorm2, isDenorm3, isDenorm4, Denorm1, Denorm2;
    wire             M_RightBig, M_LeftBig, M_Equal, MA0, MB0;

    assign MA = alpha[22:0];
    assign MB = bravo[22:0];
    assign M_LeftBig = MA > MB;
    assign M_RightBig = MA < MB;
    assign M_Equal = (MA == MB);

    assign MA0 = ((MA==23'd0) ? 1'b1 : 1'b0); 
    assign MB0 = ((MB==23'd0) ? 1'b1 : 1'b0);
    assign isDenorm1 = {~EA0, MA};
    assign isDenorm2 = {1'b0, MA};
    assign isDenorm3 = {~EB0, MB};
    assign isDenorm4 = {1'b0, MB};
    assign Denorm1 = ((EA0&&(!MA0)) ? isDenorm2 : isDenorm1);
    assign Denorm2 = ((EB0&&(!MB0)) ? isDenorm4 : isDenorm3);

    /******************************** Multiply Mantissa ******************************/
    wire            [47:0]  M_48_Original;
    wire signed     [7:0]   leading_1_position;
    wire signed     [7:0]   Until_46th;
    wire signed     [8:0]   E, Exp, Until_126, Until_126_2;

    assign M_48_Original = Denorm1 * Denorm2; // reg, wire는 기본적으로 unsigned이다.
    leading_1_detector_48bit leading_1_detector_48bit_1(
        .tmp(M_48_Original),
        .ret(leading_1_position)
    );

    assign E = EA_plus_EB_minus_254; // SIGNED 관련 오류 뜰 가능성 농후
    assign Exp = E + 9'd127;

    assign Until_46th = 8'd46 - leading_1_position;
    assign Until_126 = -9'd126 - E;

    wire        [47:0]  Man1, Man2, Man3, Man4, Man5_tmp, Man5, Man3_tmp;
    wire signed [8:0]   Exp1, Exp2, Exp3, Exp4, Exp5;
    reg         [47:0]  final_Man;
    reg         [8:0]   final_Exp;

    assign Man1 = M_48_Original;

    assign Man2 = M_48_Original>>1;
    assign Man3_tmp = M_48_Original>>Until_126; // Until 126, Until 46은 모두 음수가 가능한 수다!!!
    /*
        Man3 = M_48_Original>>Until_126;
        if(Until_126 > 48) Man3 = 0x00;
    */
    assign Man3 = (Until_126[8] ? M_48_Original : Man3_tmp);
        // if(Until_126 > 48) Man3 = 0x00;
    assign Man4 = M_48_Original<<Until_46th;
    assign Man5_tmp = M_48_Original<<Until_46th;
        // int Until_126_2 = leading_1_detector_48bit(Man5);
    assign Until_126_2 = -126 - (Exp - Until_46th);
    assign Man5 = (Until_126_2 > 9'd48) ? 48'd0 : (Man5_tmp >> Until_126_2);
    
    assign Exp1 = Exp;
    assign Exp2 = Exp + 1;
    assign Exp3 = 0;
    assign Exp4 = 1;
    assign Exp5 = Exp - Until_46th;

    `ifdef DEBUG
    reg [7:0]   DEBUG_FINAL_MAN = 8'd0;
    reg [7:0]   DEBUG_FINAL_EXP = 8'd0;
    `endif
    reg [8:0]   DEBUG_E_plus_126      =   E + 9'd126; 
    reg         DEBUG_ELB       =   ~DEBUG_E_plus_126[8]; // E > -126
    reg         DEBUG_ERB       =   DEBUG_E_plus_126[8]; // E < -126
    reg         DEBUG_EEQ       =   (DEBUG_E_plus_126 == 0); // E == -126, ELB ^ EEQ 해도 됨.
    // ******************************************** final_Man Setter *****************************/
    always_comb begin
        if(DEBUG_ELB) begin
            if(leading_1_position == 8'd47) begin // a
                final_Man = Man2;
                `ifdef DEBUG
                DEBUG_FINAL_MAN = 8'd1;
                `endif
            end
            else if(leading_1_position == 8'd46) begin // b
                final_Man = Man1;
                `ifdef DEBUG
                DEBUG_FINAL_MAN = 8'd2;
                `endif
            end 
            else begin // c
                if(E - Until_46th < -9'd126) begin // c-e-i
                    final_Man = Man5;
                    `ifdef DEBUG
                    DEBUG_FINAL_MAN = 8'd3;
                    `endif
                end
                else begin // c-b or c-h
                    final_Man = Man4; 
                    `ifdef DEBUG
                    DEBUG_FINAL_MAN = 8'd4;
                    `endif
                end
            end
        end
        else if(DEBUG_ERB) begin
            if(leading_1_position == 8'd47) begin // d
                final_Man = Man3;
                `ifdef DEBUG
                DEBUG_FINAL_MAN = 8'd5;
                `endif
            end
            else if(leading_1_position == 8'd46) begin // e
                final_Man = Man3;
                `ifdef DEBUG
                DEBUG_FINAL_MAN = 8'd6;
                `endif
            end
            else begin // f
                final_Man = Man3;
                `ifdef DEBUG
                DEBUG_FINAL_MAN = 8'd7;
                `endif
            end
        end
        else begin// Equal
            if(leading_1_position == 8'd47) begin // g
                final_Man = Man2;
                `ifdef DEBUG
                DEBUG_FINAL_MAN = 8'd8;
                `endif
            end
            else if(leading_1_position == 8'd46) begin // h
                final_Man = Man1;
                `ifdef DEBUG
                DEBUG_FINAL_MAN = 8'd9;
                `endif
            end
            else begin // i
                final_Man = Man1;
                `ifdef DEBUG
                DEBUG_FINAL_MAN = 8'hA;
                `endif
            end
        end
    end

    // ******************************************** final_Exp Setter *****************************/
    always_comb begin
        if(DEBUG_ELB) begin
            if(leading_1_position == 8'd47) begin // a
                final_Exp = Exp2;
                `ifdef DEBUG
                DEBUG_FINAL_EXP = 8'd1;
                `endif
            end
            else if(leading_1_position == 8'd46) begin // b
                final_Exp = Exp1;
                `ifdef DEBUG
                DEBUG_FINAL_EXP = 8'd2;
                `endif
            end
            else begin // c
                if(E-Until_46th > -9'd126) begin // c-b
                    final_Exp = Exp5;
                    `ifdef DEBUG
                    DEBUG_FINAL_EXP = 8'd3;
                    `endif
                end
                else if(E-Until_46th == -9'd126) begin // c-h
                    final_Exp = Exp4;
                    `ifdef DEBUG
                    DEBUG_FINAL_EXP = 8'd4;
                    `endif
                end
                else begin // c-e-i
                    final_Exp = Exp3;
                    `ifdef DEBUG
                    DEBUG_FINAL_EXP = 8'd5;
                    `endif
                end
            end
        end
        else if(DEBUG_ERB) begin
            if(leading_1_position == 8'd47) begin // d
                if(Until_126 == 1) begin // d-h
                    final_Exp = Exp4;
                    `ifdef DEBUG
                    DEBUG_FINAL_EXP = 8'd6;
                    `endif
                end
                else begin // d-i
                    final_Exp = Exp3;
                    `ifdef DEBUG
                    DEBUG_FINAL_EXP = 8'd7;
                    `endif
                end
                
            end
            else if(leading_1_position == 8'd46) begin // e
                final_Exp = Exp3;
                `ifdef DEBUG
                DEBUG_FINAL_EXP = 8'd8;
                `endif
            end
            else begin // f
                final_Exp = Exp3;
                `ifdef DEBUG
                DEBUG_FINAL_EXP = 8'd9;
                `endif
            end
        end
        else begin// Equal
            if(leading_1_position == 8'd47) begin // g
                final_Exp = Exp2;
                `ifdef DEBUG
                DEBUG_FINAL_EXP = 8'hA;
                `endif
            end
            else if(leading_1_position == 8'd46) begin // h
                final_Exp = Exp1;
                `ifdef DEBUG
                DEBUG_FINAL_EXP = 8'hB;
                `endif
            end
            else begin // i
                final_Exp = Exp3;
                `ifdef DEBUG
                DEBUG_FINAL_EXP = 8'hC;
                `endif
            end
        end
    end
    
    // ******************************************** Renormalizer *****************************/
    wire    [47:0]  M_48_46th_Hidden, M_48_46th_Hidden_RSh23, M_48_46th_Hidden_RSh23_plus_1, M_48_46th_Hidden_RSh23_plus_1_RSh1;
    wire            G, R, S;
    assign  M_48_46th_Hidden = {2'b00, final_Man[45:0] };
    assign  G = M_48_46th_Hidden[23];
    assign  R = M_48_46th_Hidden[22];
    assign  S = (M_48_46th_Hidden[21:0] == 22'd0) ? 1'b0 : 1'b1;

    assign M_48_46th_Hidden_RSh23 = M_48_46th_Hidden >> 48'd23;
    assign M_48_46th_Hidden_RSh23_plus_1 = M_48_46th_Hidden_RSh23 + 48'd1;
    assign M_48_46th_Hidden_RSh23_plus_1_RSh1 = M_48_46th_Hidden_RSh23_plus_1 >> 48'd1;

    wire signed [8:0]   final_Exp_plus1;
    assign  final_Exp_plus1 = final_Exp + 9'd1;
    
    reg     [22:0]  delta_mantissa;
    reg     [7:0]   delta_exp;

    wire            NAN, OVFL;
    assign  NAN     = ((EA == 8'hFF && MA != 0) || (EB == 8'hFF && MB != 0)) ? 1'b1 : 1'b0;
    assign OVFL     = (final_Exp > 9'd254) ? 1 : 0;

    always_comb begin
        if((R & S) | (G & R & (~S))) begin
            if(M_48_46th_Hidden_RSh23_plus_1[23]) begin
                delta_mantissa = M_48_46th_Hidden_RSh23_plus_1_RSh1[22:0];
                delta_exp = final_Exp_plus1[7:0];
            end
            else begin
                delta_mantissa = M_48_46th_Hidden_RSh23_plus_1[22:0];
                delta_exp = final_Exp[7:0];
            end
        end
        else begin
            delta_mantissa = M_48_46th_Hidden_RSh23[22:0];
            delta_exp = final_Exp[7:0];
        end
    end


    always_comb begin
        delta[31] = final_sign;
        if(NAN) begin
            delta[30:23]    =   8'hFF;
            delta[22:0]     =   23'h7FFFFF;
        end
        else if(OVFL) begin
            delta[30:23]    =   8'hFF;
            delta[22:0]     =   23'd0;
        end
        else begin
            delta[30:23]    =   delta_exp;
            delta[22:0]     =   delta_mantissa;
        end
    end

endmodule

Workspace/top.vcd
$version Generated by VerilatedVcd $end
$date Wed Sep 28 16:47:10 2022 $end
$timescale 1ps $end

 $scope module TOP $end
  $var wire 32 S alpha [31:0] $end
  $var wire 32 T bravo [31:0] $end
  $var wire 32 U delta [31:0] $end
  $scope module FP32_Multiplier_Combinatorial $end
   $var wire  1 C DEBUG_EEQ $end
   $var wire  1 A DEBUG_ELB $end
   $var wire  1 B DEBUG_ERB $end
   $var wire  9 @ DEBUG_E_plus_126 [8:0] $end
   $var wire  8 ? DEBUG_FINAL_EXP [7:0] $end
   $var wire  8 > DEBUG_FINAL_MAN [7:0] $end
   $var wire 24 k Denorm1 [23:0] $end
   $var wire 24 l Denorm2 [23:0] $end
   $var wire  9 & E [8:0] $end
   $var wire  8 # EA [7:0] $end
   $var wire  1 \ EA0 $end
   $var wire  1 ^ EA1 $end
   $var wire  8 V EA_Original [7:0] $end
   $var wire  8 Y EA_minus_EB [7:0] $end
   $var wire  9 % EA_plus_EB [8:0] $end
   $var wire  9 & EA_plus_EB_minus_254 [8:0] $end
   $var wire  8 $ EB [7:0] $end
   $var wire  1 ] EB0 $end
   $var wire  1 _ EB1 $end
   $var wire  8 W EB_Original [7:0] $end
   $var wire  8 Z EB_minus_EA [7:0] $end
   $var wire  1 a E_Equal $end
   $var wire  1 ' E_LeftBig $end
   $var wire  1 ` E_RightBig $end
   $var wire  9 , Exp [8:0] $end
   $var wire  9 , Exp1 [8:0] $end
   $var wire  9 9 Exp2 [8:0] $end
   $var wire  9 s Exp3 [8:0] $end
   $var wire  9 t Exp4 [8:0] $end
   $var wire  9 : Exp5 [8:0] $end
   $var wire  1 L G $end
   $var wire  8 X Larger_E [7:0] $end
   $var wire 23 e MA [22:0] $end
   $var wire  1 p MA0 $end
   $var wire 23 f MB [22:0] $end
   $var wire  1 q MB0 $end
   $var wire 48 D M_48_46th_Hidden [47:0] $end
   $var wire 48 F M_48_46th_Hidden_RSh23 [47:0] $end
   $var wire 48 H M_48_46th_Hidden_RSh23_plus_1 [47:0] $end
   $var wire 48 J M_48_46th_Hidden_RSh23_plus_1_RSh1 [47:0] $end
   $var wire 48 ( M_48_Original [47:0] $end
   $var wire  1 o M_Equal $end
   $var wire  1 n M_LeftBig $end
   $var wire  1 m M_RightBig $end
   $var wire 48 ( Man1 [47:0] $end
   $var wire 48 / Man2 [47:0] $end
   $var wire 48 1 Man3 [47:0] $end
   $var wire 48 7 Man3_tmp [47:0] $end
   $var wire 48 3 Man4 [47:0] $end
   $var wire 48 5 Man5 [47:0] $end
   $var wire 48 3 Man5_tmp [47:0] $end
   $var wire  1 r NAN $end
   $var wire  1 R OVFL $end
   $var wire  1 M R $end
   $var wire  8 [ Right_Shift [7:0] $end
   $var wire  1 N S $end
   $var wire  1 b SA $end
   $var wire  1 c SB $end
   $var wire  9 - Until_126 [8:0] $end
   $var wire  9 . Until_126_2 [8:0] $end
   $var wire  8 + Until_46th [7:0] $end
   $var wire 32 S alpha [31:0] $end
   $var wire 32 T bravo [31:0] $end
   $var wire 32 U delta [31:0] $end
   $var wire  8 Q delta_exp [7:0] $end
   $var wire 23 P delta_mantissa [22:0] $end
   $var wire  9 = final_Exp [8:0] $end
   $var wire  9 O final_Exp_plus1 [8:0] $end
   $var wire 48 ; final_Man [47:0] $end
   $var wire  1 d final_sign $end
   $var wire 24 g isDenorm1 [23:0] $end
   $var wire 24 h isDenorm2 [23:0] $end
   $var wire 24 i isDenorm3 [23:0] $end
   $var wire 24 j isDenorm4 [23:0] $end
   $var wire  8 * leading_1_position [7:0] $end
   $scope module leading_1_detector_48bit_1 $end
    $var wire  8 * ret [7:0] $end
    $var wire 48 ( tmp [47:0] $end
   $upscope $end
  $upscope $end
 $upscope $end
$enddefinitions $end


#0
b11001000 #
b11001100 $
b110010100 %
b010010110 &
0'
b100001000001001111110001000000001111111100101011 (
b00101111 *
b11111111 +
b100010101 ,
b011101100 -
b001101100 .
b010000100000100111111000100000000111111110010101 /
b000000000000000000000000000000000000000000000000 1
b000000000000000000000000000000000000000000000000 3
b000000000000000000000000000000000000000000000000 5
b000000000000000000000000000000000000000000000000 7
b100010110 9
b100010110 :
b000000000000000000000000000000000000000000000000 ;
b000000000 =
b00000101 >
b00000111 ?
b100010100 @
0A
1B
0C
b000000000000000000000000000000000000000000000000 D
b000000000000000000000000000000000000000000000000 F
b000000000000000000000000000000000000000000000001 H
b000000000000000000000000000000000000000000000000 J
0L
0M
0N
b000000001 O
b00000000000000000000000 P
b00000000 Q
0R
b01100100001111001001100001101001 S
b01100110001100110100100001110011 T
b00000000000000000000000000000000 U
b11001000 V
b11001100 W
b11001100 X
b11111100 Y
b00000100 Z
b00000100 [
0\
0]
0^
0_
1`
0a
0b
0c
0d
b01111001001100001101001 e
b01100110100100001110011 f
b101111001001100001101001 g
b001111001001100001101001 h
b101100110100100001110011 i
b001100110100100001110011 j
b101111001001100001101001 k
b101100110100100001110011 l
0m
1n
0o
0p
0q
0r
b000000000 s
b000000001 t
#1
b11010111 #
b01100100 $
b100111011 %
b000111101 &
1'
b100010001010000010000010001100011100001010101010 (
b010111100 ,
b101000101 -
b011000101 .
b010001000101000001000001000110001110000101010101 /
b100010001010000010000010001100011100001010101010 1
b010111101 9
b010111101 :
b010001000101000001000001000110001110000101010101 ;
b010111101 =
b00000001 >
b00000001 ?
b010111011 @
1A
0B
b000001000101000001000001000110001110000101010101 D
b000000000000000000000000000010001010000010000010 F
b000000000000000000000000000010001010000010000011 H
b000000000000000000000000000001000101000001000001 J
1N
b010111110 O
b00010001010000010000010 P
b10111101 Q
b01101011100010110100010101100111 S
b00110010011110110010001111000110 T
b01011110100010001010000010000010 U
b11010111 V
b01100100 W
b11010111 X
b01110011 Y
b10001101 Z
b01110011 [
0`
b00010110100010101100111 e
b11110110010001111000110 f
b100010110100010101100111 g
b000010110100010101100111 h
b111110110010001111000110 i
b011110110010001111000110 j
b100010110100010101100111 k
b111110110010001111000110 l
1m
0n
#2
b01111110 #
b01111110 $
b011111100 %
b111111110 &
0'
b011000000000000000000000000000000000000000000000 (
b00101110 *
b00000000 +
b001111101 ,
b110000100 -
b100000101 .
b001100000000000000000000000000000000000000000000 /
b011000000000000000000000000000000000000000000000 1
b011000000000000000000000000000000000000000000000 3
b001111110 9
b001111101 :
b011000000000000000000000000000000000000000000000 ;
b001111101 =
b00000010 >
b00000010 ?
b001111100 @
b001000000000000000000000000000000000000000000000 D
b000000000000000000000000010000000000000000000000 F
b000000000000000000000000010000000000000000000001 H
b000000000000000000000000001000000000000000000000 J
0N
b001111110 O
b10000000000000000000000 P
b01111101 Q
b00111111000000000000000000000000 S
b00111111010000000000000000000000 T
b00111110110000000000000000000000 U
b01111110 V
b01111110 W
b01111110 X
b00000000 Y
b00000000 Z
b00000000 [
1a
b00000000000000000000000 e
b10000000000000000000000 f
b100000000000000000000000 g
b000000000000000000000000 h
b110000000000000000000000 i
b010000000000000000000000 j
b100000000000000000000000 k
b110000000000000000000000 l
1p
#3
b00000001 #
b00000001 $
b000000010 %
b100000100 &
b000000000000000000000000000000000000000000000000 (
b11111111 *
b00101111 +
b110000011 ,
b001111110 -
b000101110 .
b000000000000000000000000000000000000000000000000 /
b000000000000000000000000000000000000000000000000 1
b000000000000000000000000000000000000000000000000 3
b110000100 9
b101010100 :
b000000000000000000000000000000000000000000000000 ;
b000000000 =
b00000111 >
b00001001 ?
b110000010 @
0A
1B
b000000000000000000000000000000000000000000000000 D
b000000000000000000000000000000000000000000000000 F
b000000000000000000000000000000000000000000000001 H
b000000000000000000000000000000000000000000000000 J
b000000001 O
b00000000000000000000000 P
b00000000 Q
b00000000000000000000000000000000 S
b00000000000000000000000000000000 T
b00000000000000000000000000000000 U
b00000000 V
b00000000 W
b00000000 X
1\
1]
b00000000000000000000000 f
b000000000000000000000000 g
b000000000000000000000000 i
b000000000000000000000000 j
b000000000000000000000000 k
b000000000000000000000000 l
0m
1o
1q
#4
b01111110 #
b01111101 $
b011111011 %
b111111101 &
1'
b011100000000000000000000000000000000000000000000 (
b00101110 *
b00000000 +
b001111100 ,
b110000101 -
b100000110 .
b001110000000000000000000000000000000000000000000 /
b011100000000000000000000000000000000000000000000 1
b011100000000000000000000000000000000000000000000 3
b001111101 9
b001111100 :
b011100000000000000000000000000000000000000000000 ;
b001111100 =
b00000010 >
b00000010 ?
b001111011 @
1A
0B
b001100000000000000000000000000000000000000000000 D
b000000000000000000000000011000000000000000000000 F
b000000000000000000000000011000000000000000000001 H
b000000000000000000000000001100000000000000000000 J
b001111101 O
b11000000000000000000000 P
b01111100 Q
b00111111000000000000000000000000 S
b00111110111000000000000000000000 T
b00111110011000000000000000000000 U
b01111110 V
b01111101 W
b01111110 X
b00000001 Y
b11111111 Z
b00000001 [
0\
0]
0a
b11000000000000000000000 f
b100000000000000000000000 g
b111000000000000000000000 i
b011000000000000000000000 j
b100000000000000000000000 k
b111000000000000000000000 l
1m
0o
0q
#5
b00000001 #
b00000001 $
b000000010 %
b100000100 &
0'
b000000000000000000000000000000000000000000000000 (
b11111111 *
b00101111 +
b110000011 ,
b001111110 -
b000101110 .
b000000000000000000000000000000000000000000000000 /
b000000000000000000000000000000000000000000000000 1
b000000000000000000000000000000000000000000000000 3
b110000100 9
b101010100 :
b000000000000000000000000000000000000000000000000 ;
b000000000 =
b00000111 >
b00001001 ?
b110000010 @
0A
1B
b000000000000000000000000000000000000000000000000 D
b000000000000000000000000000000000000000000000000 F
b000000000000000000000000000000000000000000000001 H
b000000000000000000000000000000000000000000000000 J
b000000001 O
b00000000000000000000000 P
b00000000 Q
b00000000000000000000000000000000 S
b00000000000000000000000000000000 T
b00000000000000000000000000000000 U
b00000000 V
b00000000 W
b00000000 X
b00000000 Y
b00000000 Z
b00000000 [
1\
1]
1a
b00000000000000000000000 f
b000000000000000000000000 g
b000000000000000000000000 i
b000000000000000000000000 j
b000000000000000000000000 k
b000000000000000000000000 l
0m
1o
1q
#6
b01111110 #
b01111110 $
b011111100 %
b111111110 &
b011000000000000000000000000000000000000000000000 (
b00101110 *
b00000000 +
b001111101 ,
b110000100 -
b100000101 .
b001100000000000000000000000000000000000000000000 /
b011000000000000000000000000000000000000000000000 1
b011000000000000000000000000000000000000000000000 3
b001111110 9
b001111101 :
b011000000000000000000000000000000000000000000000 ;
b001111101 =
b00000010 >
b00000010 ?
b001111100 @
1A
0B
b001000000000000000000000000000000000000000000000 D
b000000000000000000000000010000000000000000000000 F
b000000000000000000000000010000000000000000000001 H
b000000000000000000000000001000000000000000000000 J
b001111110 O
b10000000000000000000000 P
b01111101 Q
b10111111000000000000000000000000 S
b00111111010000000000000000000000 T
b10111110110000000000000000000000 U
b01111110 V
b01111110 W
b01111110 X
0\
0]
1b
1d
b10000000000000000000000 f
b100000000000000000000000 g
b110000000000000000000000 i
b010000000000000000000000 j
b100000000000000000000000 k
b110000000000000000000000 l
1m
0o
0q
#7
b11010111 #
b01100100 $
b100111011 %
b000111101 &
1'
b100010001010000010000010001100011100001010101010 (
b00101111 *
b11111111 +
b010111100 ,
b101000101 -
b011000101 .
b010001000101000001000001000110001110000101010101 /
b100010001010000010000010001100011100001010101010 1
b000000000000000000000000000000000000000000000000 3
b010111101 9
b010111101 :
b010001000101000001000001000110001110000101010101 ;
b010111101 =
b00000001 >
b00000001 ?
b010111011 @
b000001000101000001000001000110001110000101010101 D
b000000000000000000000000000010001010000010000010 F
b000000000000000000000000000010001010000010000011 H
b000000000000000000000000000001000101000001000001 J
1N
b010111110 O
b00010001010000010000010 P
b10111101 Q
b01101011100010110100010101100111 S
b00110010011110110010001111000110 T
b01011110100010001010000010000010 U
b11010111 V
b01100100 W
b11010111 X
b01110011 Y
b10001101 Z
b01110011 [
0a
0b
0d
b00010110100010101100111 e
b11110110010001111000110 f
b100010110100010101100111 g
b000010110100010101100111 h
b111110110010001111000110 i
b011110110010001111000110 j
b100010110100010101100111 k
b111110110010001111000110 l
0p
#8
b11001000 #
b11001100 $
b110010100 %
b010010110 &
0'
b100001000001001111110001000000001111111100101011 (
b100010101 ,
b011101100 -
b001101100 .
b010000100000100111111000100000000111111110010101 /
b000000000000000000000000000000000000000000000000 1
b100010110 9
b100010110 :
b000000000000000000000000000000000000000000000000 ;
b000000000 =
b00000101 >
b00000111 ?
b100010100 @
0A
1B
b000000000000000000000000000000000000000000000000 D
b000000000000000000000000000000000000000000000000 F
b000000000000000000000000000000000000000000000001 H
b000000000000000000000000000000000000000000000000 J
0N
b000000001 O
b00000000000000000000000 P
b00000000 Q
b01100100001111001001100001101001 S
b01100110001100110100100001110011 T
b00000000000000000000000000000000 U
b11001000 V
b11001100 W
b11001100 X
b11111100 Y
b00000100 Z
b00000100 [
1`
b01111001001100001101001 e
b01100110100100001110011 f
b101111001001100001101001 g
b001111001001100001101001 h
b101100110100100001110011 i
b001100110100100001110011 j
b101111001001100001101001 k
b101100110100100001110011 l
0m
1n
#9
b11101001 #
b00110010 $
b100011011 %
b000011101 &
1'
b100010110001110100111010111100011001000010101111 (
b010011100 ,
b101100101 -
b011100101 .
b010001011000111010011101011110001100100001010111 /
b100010110001110100111010111100011001000010101111 1
b010011101 9
b010011101 :
b010001011000111010011101011110001100100001010111 ;
b010011101 =
b00000001 >
b00000001 ?
b010011011 @
1A
0B
b000001011000111010011101011110001100100001010111 D
b000000000000000000000000000010110001110100111010 F
b000000000000000000000000000010110001110100111011 H
b000000000000000000000000000001011000111010011101 J
1M
1N
b010011110 O
b00010110001110100111011 P
b10011101 Q
b01110100101100001101110001010001 S
b00011001010010010101110011111111 T
b01001110100010110001110100111011 U
b11101001 V
b00110010 W
b11101001 X
b10110111 Y
b01001001 Z
b10110111 [
0`
b01100001101110001010001 e
b10010010101110011111111 f
b101100001101110001010001 g
b001100001101110001010001 h
b110010010101110011111111 i
b010010010101110011111111 j
b101100001101110001010001 k
b110010010101110011111111 l
1m
0n
#10
b01010101 #
b11000100 $
b100011001 %
b000011011 &
0'
b110000011101010000101010111101000010010000111000 (
b010011010 ,
b101100111 -
b011100111 .
b011000001110101000010101011110100001001000011100 /
b110000011101010000101010111101000010010000111000 1
b010011011 9
b010011011 :
b011000001110101000010101011110100001001000011100 ;
b010011011 =
b010011001 @
b001000001110101000010101011110100001001000011100 D
b000000000000000000000000010000011101010000101010 F
b000000000000000000000000010000011101010000101011 H
b000000000000000000000000001000001110101000010101 J
b010011100 O
b10000011101010000101011 P
b10011011 Q
b00101010111010001001010001001010 S
b01100010010101010101100011101100 T
b01001101110000011101010000101011 U
b01010101 V
b11000100 W
b11000100 X
b10010001 Y
b01101111 Z
b01101111 [
1`
b11010001001010001001010 e
b10101010101100011101100 f
b111010001001010001001010 g
b011010001001010001001010 h
b110101010101100011101100 i
b010101010101100011101100 j
b111010001001010001001010 k
b110101010101100011101100 l
0m
1n
#11
b01000111 #
b10001101 $
b011010100 %
b111010110 &
b100000010001000110000110000011101100111111010101 (
b001010101 ,
b110101100 -
b100101100 .
b010000001000100011000011000001110110011111101010 /
b100000010001000110000110000011101100111111010101 1
b001010110 9
b001010110 :
b010000001000100011000011000001110110011111101010 ;
b001010110 =
b001010100 @
b000000001000100011000011000001110110011111101010 D
b000000000000000000000000000000010001000110000110 F
b000000000000000000000000000000010001000110000111 H
b000000000000000000000000000000001000100011000011 J
0M
b001010111 O
b00000010001000110000110 P
b01010110 Q
b00100011100011100001111100101001 S
b01000110111010000111110011001101 T
b00101011000000010001000110000110 U
b01000111 V
b10001101 W
b10001101 X
b10111010 Y
b01000110 Z
b01000110 [
b00011100001111100101001 e
b11010000111110011001101 f
b100011100001111100101001 g
b000011100001111100101001 h
b111010000111110011001101 i
b011010000111110011001101 j
b100011100001111100101001 k
b111010000111110011001101 l
1m
0n
