Workspace/top.sv
module leading_1_detector_48bit
    (
        input wire  [47:0]  tmp,
        output reg  [7:0]   ret
    );
    always_comb begin
        if(tmp[47]) begin
            ret = 8'd47;
        end
        else if(tmp[46]) begin
        ret = 8'd46;
        end
        else if(tmp[45]) begin
        ret = 8'd45;
        end
        else if(tmp[44]) begin
        ret = 8'd44;
        end
        else if(tmp[43]) begin
        ret = 8'd43;
        end
        else if(tmp[42]) begin
        ret = 8'd42;
        end
        else if(tmp[41]) begin
        ret = 8'd41;
        end
        else if(tmp[40]) begin
        ret = 8'd40;
        end
        else if(tmp[39]) begin
        ret = 8'd39;
        end
        else if(tmp[38]) begin
        ret = 8'd38;
        end
        else if(tmp[37]) begin
        ret = 8'd37;
        end
        else if(tmp[36]) begin
        ret = 8'd36;
        end
        else if(tmp[35]) begin
        ret = 8'd35;
        end
        else if(tmp[34]) begin
        ret = 8'd34;
        end
        else if(tmp[33]) begin
        ret = 8'd33;
        end
        else if(tmp[32]) begin
        ret = 8'd32;
        end
        else if(tmp[31]) begin
        ret = 8'd31;
        end
        else if(tmp[30]) begin
        ret = 8'd30;
        end
        else if(tmp[29]) begin
        ret = 8'd29;
        end
        else if(tmp[28]) begin
        ret = 8'd28;
        end
        else if(tmp[27]) begin
        ret = 8'd27;
        end
        else if(tmp[26]) begin
        ret = 8'd26;
        end
        else if(tmp[25]) begin
        ret = 8'd25;
        end
        else if(tmp[24]) begin
        ret = 8'd24;
        end
        else if(tmp[23]) begin
        ret = 8'd23;
        end
        else if(tmp[22]) begin
        ret = 8'd22;
        end
        else if(tmp[21]) begin
        ret = 8'd21;
        end
        else if(tmp[20]) begin
        ret = 8'd20;
        end
        else if(tmp[19]) begin
        ret = 8'd19;
        end
        else if(tmp[18]) begin
        ret = 8'd18;
        end
        else if(tmp[17]) begin
        ret = 8'd17;
        end
        else if(tmp[16]) begin
        ret = 8'd16;
        end
        else if(tmp[15]) begin
        ret = 8'd15;
        end
        else if(tmp[14]) begin
        ret = 8'd14;
        end
        else if(tmp[13]) begin
        ret = 8'd13;
        end
        else if(tmp[12]) begin
        ret = 8'd12;
        end
        else if(tmp[11]) begin
        ret = 8'd11;
        end
        else if(tmp[10]) begin
        ret = 8'd10;
        end
        else if(tmp[9]) begin
        ret = 8'd9;
        end
        else if(tmp[8]) begin
        ret = 8'd8;
        end
        else if(tmp[7]) begin
        ret = 8'd7;
        end
        else if(tmp[6]) begin
        ret = 8'd6;
        end
        else if(tmp[5]) begin
        ret = 8'd5;
        end
        else if(tmp[4]) begin
        ret = 8'd4;
        end
        else if(tmp[3]) begin
        ret = 8'd3;
        end
        else if(tmp[2]) begin
        ret = 8'd2;
        end
        else if(tmp[1]) begin
        ret = 8'd1;
        end
        else if(tmp[0]) begin
        ret = 8'd0;
        end
        else begin
        ret = 8'hFF;
        end
    end
endmodule

module FP32_Multiplier_Combinatorial
    (
        input wire [31:0] alpha,
        input wire [31:0] bravo,
        output reg [31:0] delta
        // VALID, READY handshake 는 어떻게 구현?
    );

    /*
        IEEE 754 Floating Point
        1 Bit | 8 Bit | 23 Bit
    */

    // 기본적으로, EA 및 EB는 unsigned 취급.
    wire [7:0]   EA_Original, EB_Original, EA, EB;
    wire signed [7:0]   Larger_E, EA_minus_EB, EB_minus_EA, Right_Shift;
    wire signed [8:0]   EA_plus_EB, EA_plus_EB_minus_254;
    wire         EA0, EB0, EA1, EB1, E_LeftBig, E_RightBig, E_Equal;

    assign EA_Original = alpha[30:23];
    assign EB_Original = bravo[30:23];

    assign EA0 = ((EA_Original == 8'd0) ? 1'b1 : 1'b0);
    assign EB0 = ((EB_Original == 8'd0) ? 1'b1 : 1'b0);
    assign EA1 = ((EA_Original == 8'hFF) ? 1'b1 : 1'b0);
    assign EB1 = ((EB_Original == 8'hFF) ? 1'b1 : 1'b0);

    assign EA_minus_EB = EA_Original - EB_Original;
    assign EB_minus_EA = EB_Original - EA_Original;

    assign E_RightBig = ((EA_Original < EB_Original) ? 1'b1 : 1'b0);
    assign E_LeftBig = ((EA_Original > EB_Original) ? 1'b1 : 1'b0);
    assign E_Equal = !(E_RightBig | E_LeftBig);

    assign Larger_E = ((E_LeftBig) ? EA_Original : EB_Original);
    assign Right_Shift = ((E_LeftBig) ? EA_minus_EB : EB_minus_EA) - {7'd0 , (EA0 ^ EB0)};

    assign EA = EA_Original + {7'd0 ,EA0};
    assign EB = EB_Original + {7'd0, EB0};

    assign EA_plus_EB = EA + EB; // 9Bit 해야 안전하지 않아? 맞겠지?
    assign EA_plus_EB_minus_254 = EA_plus_EB - 8'd254;

    /********************** Get Sign ************************/
    wire SA, SB, final_sign;
    assign SA = alpha[31];
    assign SB = bravo[31];
    assign final_sign = SA ^ SB;
    /**********************　　　Setting Up Multiply Mantissa　　　　****************************/

    wire    [22:0]   MA, MB; // Hidden 1 없음에 유의
    wire    [23:0]   isDenorm1, isDenorm2, isDenorm3, isDenorm4, Denorm1, Denorm2;
    wire             M_RightBig, M_LeftBig, M_Equal, MA0, MB0;

    assign MA = alpha[22:0];
    assign MB = bravo[22:0];
    assign M_LeftBig = MA > MB;
    assign M_RightBig = MA < MB;
    assign M_Equal = (MA == MB);

    assign MA0 = ((MA==23'd0) ? 1'b1 : 1'b0); 
    assign MB0 = ((MB==23'd0) ? 1'b1 : 1'b0);
    assign isDenorm1 = {~EA0, MA};
    assign isDenorm2 = {1'b0, MA};
    assign isDenorm3 = {~EB0, MB};
    assign isDenorm4 = {1'b0, MB};
    assign Denorm1 = ((EA0&&(!MA0)) ? isDenorm2 : isDenorm1);
    assign Denorm2 = ((EB0&&(!MB0)) ? isDenorm4 : isDenorm3);

    /******************************** Multiply Mantissa ******************************/
    wire            [47:0]  M_48_Original;
    wire signed     [7:0]   leading_1_position;
    wire signed     [7:0]   Until_46th;
    wire signed     [8:0]   E, Exp, Until_126, Until_126_2;

    assign M_48_Original = Denorm1 * Denorm2; // reg, wire는 기본적으로 unsigned이다.
    leading_1_detector_48bit leading_1_detector_48bit_1(
        .tmp(M_48_Original),
        .ret(leading_1_position)
    );

    assign E = EA_plus_EB_minus_254; // SIGNED 관련 오류 뜰 가능성 농후
    assign Exp = E + 9'd127;

    assign Until_46th = 8'd46 - leading_1_position;
    assign Until_126 = -9'd126 - E;

    wire        [47:0]  Man1, Man2, Man3, Man4, Man5_tmp, Man5;
    wire signed [8:0]   Exp1, Exp2, Exp3, Exp4, Exp5;
    reg         [47:0]  final_Man;
    reg         [8:0]   final_Exp;

    assign Man1 = M_48_Original;

    assign Man2 = M_48_Original>>1;
    assign Man3 = M_48_Original>>Until_126;
        // if(Until_126 > 48) Man3 = 0x00;
    assign Man4 = M_48_Original<<Until_46th;
    assign Man5_tmp = M_48_Original<<Until_46th;
        // int Until_126_2 = leading_1_detector_48bit(Man5);
    assign Until_126_2 = -126 - (Exp - Until_46th);
    assign Man5 = (Until_126_2 > 9'd48) ? 48'd0 : (Man5_tmp >> Until_126_2);
    
    assign Exp1 = Exp;
    assign Exp2 = Exp + 1;
    assign Exp3 = 0;
    assign Exp4 = 1;
    assign Exp5 = Exp - Until_46th;


    // ******************************************** final_Man Setter *****************************/
    always_comb begin
        if(E > -9'd126) begin
            if(leading_1_position == 8'd47) begin // a
                final_Man = Man2;
            end
            else if(leading_1_position == 8'd46) begin // b
                final_Man = Man1;
            end 
            else begin // c
                if(E - Until_46th < -9'd126) begin // c-e-i
                    final_Man = Man5;
                end
                else begin // c-b or c-h
                    final_Man = Man4; 
                end
            end
        end
        else if(E < -9'd126) begin
            if(leading_1_position == 8'd47) begin // d
                final_Man = Man3;
            end
            else if(leading_1_position == 8'd46) begin // e
                final_Man = Man3;
            end
            else begin // f
                final_Man = Man3;
            end
        end
        else begin// Equal
            if(leading_1_position == 8'd47) begin // g
                final_Man = Man2;
            end
            else if(leading_1_position == 8'd46) begin // h
                    final_Man = Man1;
            end
            else begin // i
                    final_Man = Man1;
            end
        end
    end

    // ******************************************** final_Exp Setter *****************************/
    always_comb begin
        if(E > -9'd126) begin
            if(leading_1_position == 8'd47) begin // a
                final_Exp = Exp2;
            end
            else if(leading_1_position == 8'd46) begin // b
                final_Exp = Exp1;
            end
            else begin // c
                if(E-Until_46th > -9'd126) begin // c-b
                    final_Exp = Exp5;
                end
                else if(E-Until_46th == -9'd126) begin // c-h
                    final_Exp = Exp4;
                end
                else begin // c-e-i
                    final_Exp = Exp3;
                end
            end
        end
        else if(E < -9'd126) begin
            if(leading_1_position == 8'd47) begin // d
                if(Until_126 == 1) begin // d-h
                    final_Exp = Exp4;
                end
                else begin // d-i
                    final_Exp = Exp3;
                end
                
            end
            else if(leading_1_position == 8'd46) begin // e
                final_Exp = Exp3;
            end
            else begin // f
                final_Exp = Exp3;
            end
        end
        else begin// Equal
            if(leading_1_position == 8'd47) begin // g
                final_Exp = Exp2;
            end
            else if(leading_1_position == 8'd46) begin // h
                final_Exp = Exp1;
            end
            else begin // i
                final_Exp = Exp3;
            end
        end
    end
    
    // ******************************************** Renormalizer *****************************/
    wire    [47:0]  M_48_46th_Hidden, M_48_46th_Hidden_RSh23, M_48_46th_Hidden_RSh23_plus_1, M_48_46th_Hidden_RSh23_plus_1_RSh1;
    wire            G, R, S;
    assign  M_48_46th_Hidden = {2'b00, final_Man[45:0] };
    assign  G = M_48_46th_Hidden[23];
    assign  R = M_48_46th_Hidden[22];
    assign  S = (M_48_46th_Hidden[21:0] == 22'd0) ? 1'b0 : 1'b1;

    assign M_48_46th_Hidden_RSh23 = M_48_46th_Hidden >> 48'd23;
    assign M_48_46th_Hidden_RSh23_plus_1 = M_48_46th_Hidden_RSh23 + 48'd1;
    assign M_48_46th_Hidden_RSh23_plus_1_RSh1 = M_48_46th_Hidden_RSh23_plus_1 >> 48'd1;

    wire signed [8:0]   final_Exp_plus1;
    assign  final_Exp_plus1 = final_Exp + 9'd1;
    
    reg     [22:0]  delta_mantissa;
    reg     [7:0]   delta_exp;

    always_comb begin
        if((R & S) | (G & R & (~S))) begin
            if(M_48_46th_Hidden_RSh23_plus_1[23]) begin
                delta_mantissa = M_48_46th_Hidden_RSh23_plus_1_RSh1[22:0];
                delta_exp = final_Exp_plus1[7:0];
            end
            else begin
                delta_mantissa = M_48_46th_Hidden_RSh23_plus_1[22:0];
                delta_exp = final_Exp[7:0];
            end
        end
        else begin
            delta_mantissa = M_48_46th_Hidden_RSh23[22:0];
            delta_exp = final_Exp[7:0];
        end
    end

    wire            NAN, OVFL;
    assign  NAN     = ((EA == 8'hFF && MA != 0) || (EB == 8'hFF && MB != 0)) ? 1'b1 : 1'b0;
    assign  OVFL    = (delta_exp > 254) ? 1'b1 : 1'b0;

    always_comb begin
        delta[31] = final_sign;
        if(NAN) begin
            delta[30:23]    =   8'hFF;
            delta[22:0]     =   23'h7FFFFF;
        end
        else if(OVFL) begin
            delta[30:23]    =   8'hFF;
            delta[22:0]     =   23'd0;
        end
        else begin
            delta[30:23]    =   delta_exp;
            delta[22:0]     =   delta_mantissa;
        end
    end

endmodule

Workspace/top.vcd
$version Generated by VerilatedVcd $end
$date Tue Sep 27 18:20:34 2022 $end
$timescale 1ps $end

 $scope module TOP $end
  $var wire 32 K alpha [31:0] $end
  $var wire 32 L bravo [31:0] $end
  $var wire 32 M delta [31:0] $end
  $scope module FP32_Multiplier_Combinatorial $end
   $var wire 24 c Denorm1 [23:0] $end
   $var wire 24 d Denorm2 [23:0] $end
   $var wire  9 & E [8:0] $end
   $var wire  8 # EA [7:0] $end
   $var wire  1 T EA0 $end
   $var wire  1 V EA1 $end
   $var wire  8 N EA_Original [7:0] $end
   $var wire  8 Q EA_minus_EB [7:0] $end
   $var wire  9 % EA_plus_EB [8:0] $end
   $var wire  9 & EA_plus_EB_minus_254 [8:0] $end
   $var wire  8 $ EB [7:0] $end
   $var wire  1 U EB0 $end
   $var wire  1 W EB1 $end
   $var wire  8 O EB_Original [7:0] $end
   $var wire  8 R EB_minus_EA [7:0] $end
   $var wire  1 Y E_Equal $end
   $var wire  1 ' E_LeftBig $end
   $var wire  1 X E_RightBig $end
   $var wire  9 , Exp [8:0] $end
   $var wire  9 , Exp1 [8:0] $end
   $var wire  9 7 Exp2 [8:0] $end
   $var wire  9 k Exp3 [8:0] $end
   $var wire  9 l Exp4 [8:0] $end
   $var wire  9 8 Exp5 [8:0] $end
   $var wire  1 D G $end
   $var wire  8 P Larger_E [7:0] $end
   $var wire 23 ] MA [22:0] $end
   $var wire  1 h MA0 $end
   $var wire 23 ^ MB [22:0] $end
   $var wire  1 i MB0 $end
   $var wire 48 < M_48_46th_Hidden [47:0] $end
   $var wire 48 > M_48_46th_Hidden_RSh23 [47:0] $end
   $var wire 48 @ M_48_46th_Hidden_RSh23_plus_1 [47:0] $end
   $var wire 48 B M_48_46th_Hidden_RSh23_plus_1_RSh1 [47:0] $end
   $var wire 48 ( M_48_Original [47:0] $end
   $var wire  1 g M_Equal $end
   $var wire  1 f M_LeftBig $end
   $var wire  1 e M_RightBig $end
   $var wire 48 ( Man1 [47:0] $end
   $var wire 48 / Man2 [47:0] $end
   $var wire 48 1 Man3 [47:0] $end
   $var wire 48 3 Man4 [47:0] $end
   $var wire 48 5 Man5 [47:0] $end
   $var wire 48 3 Man5_tmp [47:0] $end
   $var wire  1 j NAN $end
   $var wire  1 J OVFL $end
   $var wire  1 E R $end
   $var wire  8 S Right_Shift [7:0] $end
   $var wire  1 F S $end
   $var wire  1 Z SA $end
   $var wire  1 [ SB $end
   $var wire  9 - Until_126 [8:0] $end
   $var wire  9 . Until_126_2 [8:0] $end
   $var wire  8 + Until_46th [7:0] $end
   $var wire 32 K alpha [31:0] $end
   $var wire 32 L bravo [31:0] $end
   $var wire 32 M delta [31:0] $end
   $var wire  8 I delta_exp [7:0] $end
   $var wire 23 H delta_mantissa [22:0] $end
   $var wire  9 ; final_Exp [8:0] $end
   $var wire  9 G final_Exp_plus1 [8:0] $end
   $var wire 48 9 final_Man [47:0] $end
   $var wire  1 \ final_sign $end
   $var wire 24 _ isDenorm1 [23:0] $end
   $var wire 24 ` isDenorm2 [23:0] $end
   $var wire 24 a isDenorm3 [23:0] $end
   $var wire 24 b isDenorm4 [23:0] $end
   $var wire  8 * leading_1_position [7:0] $end
   $scope module leading_1_detector_48bit_1 $end
    $var wire  8 * ret [7:0] $end
    $var wire 48 ( tmp [47:0] $end
   $upscope $end
  $upscope $end
 $upscope $end
$enddefinitions $end


#0
b01111110 #
b01111110 $
b011111100 %
b111111110 &
0'
b011000000000000000000000000000000000000000000000 (
b00101110 *
b00000000 +
b001111101 ,
b110000100 -
b100000101 .
b001100000000000000000000000000000000000000000000 /
b000000000000000000000000000000000000000000000000 1
b011000000000000000000000000000000000000000000000 3
b000000000000000000000000000000000000000000000000 5
b001111110 7
b001111101 8
b011000000000000000000000000000000000000000000000 9
b001111101 ;
b001000000000000000000000000000000000000000000000 <
b000000000000000000000000010000000000000000000000 >
b000000000000000000000000010000000000000000000001 @
b000000000000000000000000001000000000000000000000 B
0D
0E
0F
b001111110 G
b10000000000000000000000 H
b01111101 I
0J
b00111111000000000000000000000000 K
b00111111010000000000000000000000 L
b00111110110000000000000000000000 M
b01111110 N
b01111110 O
b01111110 P
b00000000 Q
b00000000 R
b00000000 S
0T
0U
0V
0W
0X
1Y
0Z
0[
0\
b00000000000000000000000 ]
b10000000000000000000000 ^
b100000000000000000000000 _
b000000000000000000000000 `
b110000000000000000000000 a
b010000000000000000000000 b
b100000000000000000000000 c
b110000000000000000000000 d
1e
0f
0g
1h
0i
0j
b000000000 k
b000000001 l
#1
b00000001 #
b00000001 $
b000000010 %
b100000100 &
b000000000000000000000000000000000000000000000000 (
b11111111 *
b00101111 +
b110000011 ,
b001111110 -
b000101110 .
b000000000000000000000000000000000000000000000000 /
b000000000000000000000000000000000000000000000000 3
b110000100 7
b101010100 8
b000000000000000000000000000000000000000000000000 9
b000000000 ;
b000000000000000000000000000000000000000000000000 <
b000000000000000000000000000000000000000000000000 >
b000000000000000000000000000000000000000000000001 @
b000000000000000000000000000000000000000000000000 B
b000000001 G
b00000000000000000000000 H
b00000000 I
b00000000000000000000000000000000 K
b00000000000000000000000000000000 L
b00000000000000000000000000000000 M
b00000000 N
b00000000 O
b00000000 P
1T
1U
b00000000000000000000000 ^
b000000000000000000000000 _
b000000000000000000000000 a
b000000000000000000000000 b
b000000000000000000000000 c
b000000000000000000000000 d
0e
1g
1i
#2
b01111110 #
b01111101 $
b011111011 %
b111111101 &
1'
b011100000000000000000000000000000000000000000000 (
b00101110 *
b00000000 +
b001111100 ,
b110000101 -
b100000110 .
b001110000000000000000000000000000000000000000000 /
b011100000000000000000000000000000000000000000000 3
b001111101 7
b001111100 8
b011100000000000000000000000000000000000000000000 9
b001111100 ;
b001100000000000000000000000000000000000000000000 <
b000000000000000000000000011000000000000000000000 >
b000000000000000000000000011000000000000000000001 @
b000000000000000000000000001100000000000000000000 B
b001111101 G
b11000000000000000000000 H
b01111100 I
b00111111000000000000000000000000 K
b00111110111000000000000000000000 L
b00111110011000000000000000000000 M
b01111110 N
b01111101 O
b01111110 P
b00000001 Q
b11111111 R
b00000001 S
0T
0U
0Y
b11000000000000000000000 ^
b100000000000000000000000 _
b111000000000000000000000 a
b011000000000000000000000 b
b100000000000000000000000 c
b111000000000000000000000 d
1e
0g
0i
#3
b00000001 #
b00000001 $
b000000010 %
b100000100 &
0'
b000000000000000000000000000000000000000000000000 (
b11111111 *
b00101111 +
b110000011 ,
b001111110 -
b000101110 .
b000000000000000000000000000000000000000000000000 /
b000000000000000000000000000000000000000000000000 3
b110000100 7
b101010100 8
b000000000000000000000000000000000000000000000000 9
b000000000 ;
b000000000000000000000000000000000000000000000000 <
b000000000000000000000000000000000000000000000000 >
b000000000000000000000000000000000000000000000001 @
b000000000000000000000000000000000000000000000000 B
b000000001 G
b00000000000000000000000 H
b00000000 I
b00000000000000000000000000000000 K
b00000000000000000000000000000000 L
b00000000000000000000000000000000 M
b00000000 N
b00000000 O
b00000000 P
b00000000 Q
b00000000 R
b00000000 S
1T
1U
1Y
b00000000000000000000000 ^
b000000000000000000000000 _
b000000000000000000000000 a
b000000000000000000000000 b
b000000000000000000000000 c
b000000000000000000000000 d
0e
1g
1i
#4
b01111110 #
b01111110 $
b011111100 %
b111111110 &
b011000000000000000000000000000000000000000000000 (
b00101110 *
b00000000 +
b001111101 ,
b110000100 -
b100000101 .
b001100000000000000000000000000000000000000000000 /
b011000000000000000000000000000000000000000000000 3
b001111110 7
b001111101 8
b011000000000000000000000000000000000000000000000 9
b001111101 ;
b001000000000000000000000000000000000000000000000 <
b000000000000000000000000010000000000000000000000 >
b000000000000000000000000010000000000000000000001 @
b000000000000000000000000001000000000000000000000 B
b001111110 G
b10000000000000000000000 H
b01111101 I
b10111111000000000000000000000000 K
b00111111010000000000000000000000 L
b10111110110000000000000000000000 M
b01111110 N
b01111110 O
b01111110 P
0T
0U
1Z
1\
b10000000000000000000000 ^
b100000000000000000000000 _
b110000000000000000000000 a
b010000000000000000000000 b
b100000000000000000000000 c
b110000000000000000000000 d
1e
0g
0i
#5
b11010111 #
b01100100 $
b100111011 %
b000111101 &
1'
b100010001010000010000010001100011100001010101010 (
b00101111 *
b11111111 +
b010111100 ,
b101000101 -
b011000101 .
b010001000101000001000001000110001110000101010101 /
b000000000000000000000000000000000000000000000000 3
b010111101 7
b010111101 8
b000000000000000000000000000000000000000000000000 9
b000000000 ;
b000000000000000000000000000000000000000000000000 <
b000000000000000000000000000000000000000000000000 >
b000000000000000000000000000000000000000000000001 @
b000000000000000000000000000000000000000000000000 B
b000000001 G
b00000000000000000000000 H
b00000000 I
b01101011100010110100010101100111 K
b00110010011110110010001111000110 L
b00000000000000000000000000000000 M
b11010111 N
b01100100 O
b11010111 P
b01110011 Q
b10001101 R
b01110011 S
0Y
0Z
0\
b00010110100010101100111 ]
b11110110010001111000110 ^
b100010110100010101100111 _
b000010110100010101100111 `
b111110110010001111000110 a
b011110110010001111000110 b
b100010110100010101100111 c
b111110110010001111000110 d
0h
#6
b11001000 #
b11001100 $
b110010100 %
b010010110 &
0'
b100001000001001111110001000000001111111100101011 (
b100010101 ,
b011101100 -
b001101100 .
b010000100000100111111000100000000111111110010101 /
b100010110 7
b100010110 8
b01100100001111001001100001101001 K
b01100110001100110100100001110011 L
b11001000 N
b11001100 O
b11001100 P
b11111100 Q
b00000100 R
b00000100 S
1X
b01111001001100001101001 ]
b01100110100100001110011 ^
b101111001001100001101001 _
b001111001001100001101001 `
b101100110100100001110011 a
b001100110100100001110011 b
b101111001001100001101001 c
b101100110100100001110011 d
0e
1f
#7
b11101001 #
b00110010 $
b100011011 %
b000011101 &
1'
b100010110001110100111010111100011001000010101111 (
b010011100 ,
b101100101 -
b011100101 .
b010001011000111010011101011110001100100001010111 /
b010011101 7
b010011101 8
b01110100101100001101110001010001 K
b00011001010010010101110011111111 L
b11101001 N
b00110010 O
b11101001 P
b10110111 Q
b01001001 R
b10110111 S
0X
b01100001101110001010001 ]
b10010010101110011111111 ^
b101100001101110001010001 _
b001100001101110001010001 `
b110010010101110011111111 a
b010010010101110011111111 b
b101100001101110001010001 c
b110010010101110011111111 d
1e
0f
#8
b01010101 #
b11000100 $
b100011001 %
b000011011 &
0'
b110000011101010000101010111101000010010000111000 (
b010011010 ,
b101100111 -
b011100111 .
b011000001110101000010101011110100001001000011100 /
b010011011 7
b010011011 8
b00101010111010001001010001001010 K
b01100010010101010101100011101100 L
b01010101 N
b11000100 O
b11000100 P
b10010001 Q
b01101111 R
b01101111 S
1X
b11010001001010001001010 ]
b10101010101100011101100 ^
b111010001001010001001010 _
b011010001001010001001010 `
b110101010101100011101100 a
b010101010101100011101100 b
b111010001001010001001010 c
b110101010101100011101100 d
0e
1f
#9
b01000111 #
b10001101 $
b011010100 %
b111010110 &
b100000010001000110000110000011101100111111010101 (
b001010101 ,
b110101100 -
b100101100 .
b010000001000100011000011000001110110011111101010 /
b001010110 7
b001010110 8
b010000001000100011000011000001110110011111101010 9
b001010110 ;
b000000001000100011000011000001110110011111101010 <
b000000000000000000000000000000010001000110000110 >
b000000000000000000000000000000010001000110000111 @
b000000000000000000000000000000001000100011000011 B
1F
b001010111 G
b00000010001000110000110 H
b01010110 I
b00100011100011100001111100101001 K
b01000110111010000111110011001101 L
b00101011000000010001000110000110 M
b01000111 N
b10001101 O
b10001101 P
b10111010 Q
b01000110 R
b01000110 S
b00011100001111100101001 ]
b11010000111110011001101 ^
b100011100001111100101001 _
b000011100001111100101001 `
b111010000111110011001101 a
b011010000111110011001101 b
b100011100001111100101001 c
b111010000111110011001101 d
1e
0f
#10
b01111010 #
b10100000 $
b100011010 %
b000011100 &
b100110101010010011100111110101000111101000111110 (
b010011011 ,
b101100110 -
b011100110 .
b010011010101001001110011111010100011110100011111 /
b010011100 7
b010011100 8
b000000000000000000000000000000000000000000000000 9
b000000000 ;
b000000000000000000000000000000000000000000000000 <
b000000000000000000000000000000000000000000000000 >
b000000000000000000000000000000000000000000000001 @
b000000000000000000000000000000000000000000000000 B
0F
b000000001 G
b00000000000000000000000 H
b00000000 I
b00111101000110110101100010111010 K
b01010000011111101101011110101011 L
b00000000000000000000000000000000 M
b01111010 N
b10100000 O
b10100000 P
b11011010 Q
b00100110 R
b00100110 S
b00110110101100010111010 ]
b11111101101011110101011 ^
b100110110101100010111010 _
b000110110101100010111010 `
b111111101101011110101011 a
b011111101101011110101011 b
b100110110101100010111010 c
b111111101101011110101011 d
#11
b01011101 #
b10000011 $
b011100000 %
b111100010 &
b011111101100101110010111100001000000010001000110 (
b00101110 *
b00000000 +
b001100001 ,
b110100000 -
b100100001 .
b001111110110010111001011110000100000001000100011 /
b011111101100101110010111100001000000010001000110 3
b001100010 7
b001100001 8
b011111101100101110010111100001000000010001000110 9
b001100001 ;
b001111101100101110010111100001000000010001000110 <
b000000000000000000000000011111011001011100101111 >
b000000000000000000000000011111011001011100110000 @
b000000000000000000000000001111101100101110011000 B
1D
1F
b001100010 G
b11111011001011100101111 H
b01100001 I
b00101110101100010100000111110010 K
b01000001101101110001111011111011 L
b00110000111111011001011100101111 M
b01011101 N
b10000011 O
b10000011 P
b01100010100000111110010 ]
b01101110001111011111011 ^
b101100010100000111110010 _
b001100010100000111110010 `
b101101110001111011111011 a
b001101110001111011111011 b
b101100010100000111110010 c
b101101110001111011111011 d
#12
b11110011 #
b11101010 $
b111011101 %
b011011111 &
1'
b101011110011010000110000111110011111011100010010 (
b00101111 *
b11111111 +
b101011110 ,
b010100011 -
b000100011 .
b010101111001101000011000011111001111101110001001 /
b000000000000000000000000000000000000000000000000 3
b101011111 7
b101011111 8
b000000000000000000000000000000000000000000000000 9
b000000000 ;
b000000000000000000000000000000000000000000000000 <
b000000000000000000000000000000000000000000000000 >
b000000000000000000000000000000000000000000000001 @
b000000000000000000000000000000000000000000000000 B
0D
0F
b000000001 G
b00000000000000000000000 H
b00000000 I
b01111001111000101010100111100011 K
b01110101010001011110000101000110 L
b00000000000000000000000000000000 M
b11110011 N
b11101010 O
b11110011 P
b00001001 Q
b11110111 R
b00001001 S
0X
b11000101010100111100011 ]
b10001011110000101000110 ^
b111000101010100111100011 _
b011000101010100111100011 `
b110001011110000101000110 a
b010001011110000101000110 b
b111000101010100111100011 c
b110001011110000101000110 d
0e
1f
#13
b10100010 #
b10110111 $
b101011001 %
b001011011 &
0'
b101101011000011001101011111011011101010111111000 (
b011011010 ,
b100100111 -
b010100111 .
b010110101100001100110101111101101110101011111100 /
b011011011 7
b011011011 8
b01010001010111110000000001111100 K
b01011011110100000110001011000010 L
b10100010 N
b10110111 O
b10110111 P
b11101011 Q
b00010101 R
b00010101 S
1X
b10111110000000001111100 ]
b10100000110001011000010 ^
b110111110000000001111100 _
b010111110000000001111100 `
b110100000110001011000010 a
b010100000110001011000010 b
b110111110000000001111100 c
b110100000110001011000010 d
#14
b00100100 #
b10011011 $
b010111111 %
b111000001 &
b011011101011111010111110011000001101110101100000 (
b00101110 *
b00000000 +
b001000000 ,
b111000001 -
b101000010 .
b001101110101111101011111001100000110111010110000 /
b011011101011111010111110011000001101110101100000 3
b001000001 7
b001000000 8
b011011101011111010111110011000001101110101100000 9
b001000000 ;
b001011101011111010111110011000001101110101100000 <
b000000000000000000000000010111010111110101111100 >
b000000000000000000000000010111010111110101111101 @
b000000000000000000000000001011101011111010111110 B
1E
1F
b001000001 G
b10111010111110101111101 H
b01000000 I
b00010010001000000000100001010100 K
b01001101101100010010011111111000 L
b00100000010111010111110101111101 M
b00100100 N
b10011011 O
b10011011 P
b10001001 Q
b01110111 R
b01110111 S
b01000000000100001010100 ]
b01100010010011111111000 ^
b101000000000100001010100 _
b001000000000100001010100 `
b101100010010011111111000 a
b001100010010011111111000 b
b101000000000100001010100 c
b101100010010011111111000 d
1e
0f
#15
b00000100 #
b00111110 $
b001000010 %
b101000100 &
b010110001000000110111111110101010110001101111000 (
b111000011 ,
b000111110 -
b110111111 .
b001011000100000011011111111010101011000110111100 /
b010110001000000110111111110101010110001101111000 3
b111000100 7
b111000011 8
b000000000000000000000000000000000000000000000000 9
b000000000 ;
b000000000000000000000000000000000000000000000000 <
b000000000000000000000000000000000000000000000000 >
b000000000000000000000000000000000000000000000001 @
b000000000000000000000000000000000000000000000000 B
0E
0F
b000000001 G
b00000000000000000000000 H
b00000000 I
b00000010000101100010001100011011 K
b00011111000101101110100111101000 L
b00000000000000000000000000000000 M
b00000100 N
b00111110 O
b00111110 P
b11000110 Q
b00111010 R
b00111010 S
b00101100010001100011011 ]
b00101101110100111101000 ^
b100101100010001100011011 _
b000101100010001100011011 `
b100101101110100111101000 a
b000101101110100111101000 b
b100101100010001100011011 c
b100101101110100111101000 d
#16
b00100011 #
b11001101 $
b011110000 %
b111110010 &
b100001110101011001110000010011011101110100111011 (
b00101111 *
b11111111 +
b001110001 ,
b110010000 -
b100010000 .
b010000111010101100111000001001101110111010011101 /
b000000000000000000000000000000000000000000000000 3
b001110010 7
b001110010 8
b010000111010101100111000001001101110111010011101 9
b001110010 ;
b000000111010101100111000001001101110111010011101 <
b000000000000000000000000000001110101011001110000 >
b000000000000000000000000000001110101011001110001 @
b000000000000000000000000000000111010101100111000 B
1F
b001110011 G
b00001110101011001110000 H
b01110010 I
b00010001100100001100110111100111 K
b01100110111011110100001110001101 L
b00111001000001110101011001110000 M
b00100011 N
b11001101 O
b11001101 P
b01010110 Q
b10101010 R
b10101010 S
b00100001100110111100111 ]
b11011110100001110001101 ^
b100100001100110111100111 _
b000100001100110111100111 `
b111011110100001110001101 a
b011011110100001110001101 b
b100100001100110111100111 c
b111011110100001110001101 d
#17
b00101000 #
b01100110 $
b010001110 %
b110010000 &
b011101001001110101101000111110010111110101111100 (
b00101110 *
b00000000 +
b000001111 ,
b111110010 -
b101110011 .
b001110100100111010110100011111001011111010111110 /
b011101001001110101101000111110010111110101111100 3
b000010000 7
b000001111 8
b011101001001110101101000111110010111110101111100 9
b000001111 ;
b001101001001110101101000111110010111110101111100 <
b000000000000000000000000011010010011101011010001 >
b000000000000000000000000011010010011101011010010 @
b000000000000000000000000001101001001110101101001 B
1D
1E
b000010000 G
b11010010011101011010010 H
b00001111 I
b00010100000011100000111101110110 K
b00110011010100100010010101011010 L
b00000111111010010011101011010010 M
b00101000 N
b01100110 O
b01100110 P
b11000010 Q
b00111110 R
b00111110 S
b00011100000111101110110 ]
b10100100010010101011010 ^
b100011100000111101110110 _
b000011100000111101110110 `
b110100100010010101011010 a
b010100100010010101011010 b
b100011100000111101110110 c
b110100100010010101011010 d
